processor/uarch_sim/src/pc.v
/*
	basic program counter
	sync reset

	ld_ct_i = 1 for load, 0 for count
	d_r_i = for add to pc, 0 for replace pc
	is_aligned = 1 for properly aligned pc, 0 for misaligned pc

*/

`timescale 1ns / 1ns

module pc_unit (
	input clk_i,
	input en_i,
	input rst_i,
	input ld_ct_i,
	input d_r_i, // add to pc or replace pc

	input [31:0] ld_i,
	output reg [31:0] pc_o,
	output is_aligned_o
);
	parameter INC_BY = 4;
	assign is_aligned_o = (pc_o % 4 == 0) ? 1'b1 : 1'b0;

	always @(posedge clk_i) begin
		if (rst_i) begin
			pc_o <= 32'h0;
		end else if (en_i) begin
			if (ld_ct_i) begin
				if (d_r_i) begin
					pc_o <= pc_o + ld_i;
				end else begin
					pc_o <= ld_i;
				end
			end else begin
				pc_o <= pc_o + INC_BY;
			end
		end
	end
	
endmodule

processor/uarch_sim/test/pc_test.v
/*
	using this as an initial testbench
*/

`timescale 1ns / 1ns

module pc_unit_test();
	
	reg clk = 0;
	reg en = 0;
	reg rst = 1;

	reg ld_ct = 0;
	reg d_r_i = 0;
	
	reg [31:0] ld;
	wire [31:0] pc_m;
	wire is_aligned;
	
	pc_unit #(.INC_BY(4))
	p(.clk_i(clk), .en_i(en), .rst_i(rst), .ld_ct_i(ld_ct), .d_r_i(d_r_i), .ld_i(ld), .pc_o(pc_m), .is_aligned_o(is_aligned));
	
	always #(1) begin
		clk <= ~clk;	
	end
	
	initial begin
		$display("Running pc_unit testbench...");
		$dumpfile("proc_dump.vcd");
		$dumpvars(0, pc_unit_test);
		
		#1;
		rst <= 1'b0;
		en <= 1'b1;
		ld_ct <= 1'b1;
		ld <= 32'h0;
		#1;
		ld_ct <= 1'b0;
		#9;
		d_r_i <= 1'b1;
		ld_ct <= 1'b1;
		ld <= 32'h1;
		#2;
		d_r_i <= 1'b0;
		ld <= 32'h3;
		#2;
		ld <= 32'h99;
		ld_ct <= 1'b0;
		#12;
		en <= 1'b0;
		#24;
		
		$display("Finished.");
		$finish;
	end
endmodule

processor/uarch_sim/proc_dump.vcd
$date
	Fri Nov 30 12:19:42 2018
$end
$version
	Icarus Verilog
$end
$timescale
	1ns
$end
$scope module pc_unit_test $end
$var wire 32 ! pc_m [31:0] $end
$var wire 1 " is_aligned $end
$var reg 1 # clk $end
$var reg 1 $ d_r_i $end
$var reg 1 % en $end
$var reg 32 & ld [31:0] $end
$var reg 1 ' ld_ct $end
$var reg 1 ( rst $end
$scope module p $end
$var wire 1 # clk_i $end
$var wire 1 $ d_r_i $end
$var wire 1 % en_i $end
$var wire 1 ' ld_ct_i $end
$var wire 32 ) ld_i [31:0] $end
$var wire 1 ( rst_i $end
$var wire 1 " is_aligned_o $end
$var reg 32 * pc_o [31:0] $end
$upscope $end
$upscope $end
$enddefinitions $end
#0
$dumpvars
bx *
bx )
1(
0'
bx &
0%
0$
0#
x"
bx !
$end
#1
1"
b0 !
b0 *
b0 &
b0 )
1'
1%
0(
1#
#2
0'
0#
#3
b100 !
b100 *
1#
#4
0#
#5
b1000 !
b1000 *
1#
#6
0#
#7
b1100 !
b1100 *
1#
#8
0#
#9
b10000 !
b10000 *
1#
#10
0#
#11
0"
b10001 !
b10001 *
1#
b1 &
b1 )
1'
1$
#12
0#
#13
b11 !
b11 *
1#
b11 &
b11 )
0$
#14
0#
#15
b111 !
b111 *
1#
0'
b10011001 &
b10011001 )
#16
0#
#17
b1011 !
b1011 *
1#
#18
0#
#19
b1111 !
b1111 *
1#
#20
0#
#21
b10011 !
b10011 *
1#
#22
0#
#23
b10111 !
b10111 *
1#
#24
0#
#25
b11011 !
b11011 *
1#
#26
0#
#27
1#
0%
