systemverilog/main.sv
module main(
	input sysclk,
	input [3:0] in_a,
	input [3:0] in_b,
	output [3:0] out
);
	
	assign out = {in_a[3:2], in_b[1], sysclk};
		
	
endmodule

systemverilog/test.sv
`define SIM_CLOCKS 1000

module test();
	
	reg simclk = 0;
	reg [3:0] in_a = 0;
	reg [3:0] in_b = 0;
	wire [3:0] out;
	
	main m(.sysclk(simclk), .in_a(in_a), .in_b(in_b), .out(out));
	integer i = 0;
	
	always #(1) begin
		simclk <= ~simclk;
		if (i++ >= `SIM_CLOCKS) begin // run for a finite amount of clocks
			$finish;
		end
	end
	
	initial begin		
		$dumpfile("dump.vcd");
		$dumpvars(0, m);
		
		@(posedge simclk);
		in_a = 1;
		@(posedge simclk);
		in_a = 0;
		
		
	end
endmodule

systemverilog/dump.vcd
$date
	Tue Sep 18 16:43:31 2018
$end
$version
	Icarus Verilog
$end
$timescale
	1s
$end
$scope module test $end
$scope module m $end
$var wire 4 ! in_a [3:0] $end
$var wire 4 " in_b [3:0] $end
$var wire 1 # sysclk $end
$var wire 4 $ out [3:0] $end
$upscope $end
$upscope $end
$enddefinitions $end
#0
$dumpvars
b0 $
0#
b0 "
b0 !
$end
#1
b1 !
b1 $
1#
#2
b0 $
0#
#3
b0 !
b1 $
1#
#4
b0 $
0#
#5
b1 $
1#
#6
b0 $
0#
#7
b1 $
1#
#8
b0 $
0#
#9
b1 $
1#
#10
b0 $
0#
#11
b1 $
1#
#12
b0 $
0#
#13
b1 $
1#
#14
b0 $
0#
#15
b1 $
1#
#16
b0 $
0#
#17
b1 $
1#
#18
b0 $
0#
#19
b1 $
1#
#20
b0 $
0#
#21
b1 $
1#
#22
b0 $
0#
#23
b1 $
1#
#24
b0 $
0#
#25
b1 $
1#
#26
b0 $
0#
#27
b1 $
1#
#28
b0 $
0#
#29
b1 $
1#
#30
b0 $
0#
#31
b1 $
1#
#32
b0 $
0#
#33
b1 $
1#
#34
b0 $
0#
#35
b1 $
1#
#36
b0 $
0#
#37
b1 $
1#
#38
b0 $
0#
#39
b1 $
1#
#40
b0 $
0#
#41
b1 $
1#
#42
b0 $
0#
#43
b1 $
1#
#44
b0 $
0#
#45
b1 $
1#
#46
b0 $
0#
#47
b1 $
1#
#48
b0 $
0#
#49
b1 $
1#
#50
b0 $
0#
#51
b1 $
1#
#52
b0 $
0#
#53
b1 $
1#
#54
b0 $
0#
#55
b1 $
1#
#56
b0 $
0#
#57
b1 $
1#
#58
b0 $
0#
#59
b1 $
1#
#60
b0 $
0#
#61
b1 $
1#
#62
b0 $
0#
#63
b1 $
1#
#64
b0 $
0#
#65
b1 $
1#
#66
b0 $
0#
#67
b1 $
1#
#68
b0 $
0#
#69
b1 $
1#
#70
b0 $
0#
#71
b1 $
1#
#72
b0 $
0#
#73
b1 $
1#
#74
b0 $
0#
#75
b1 $
1#
#76
b0 $
0#
#77
b1 $
1#
#78
b0 $
0#
#79
b1 $
1#
#80
b0 $
0#
#81
b1 $
1#
#82
b0 $
0#
#83
b1 $
1#
#84
b0 $
0#
#85
b1 $
1#
#86
b0 $
0#
#87
b1 $
1#
#88
b0 $
0#
#89
b1 $
1#
#90
b0 $
0#
#91
b1 $
1#
#92
b0 $
0#
#93
b1 $
1#
#94
b0 $
0#
#95
b1 $
1#
#96
b0 $
0#
#97
b1 $
1#
#98
b0 $
0#
#99
b1 $
1#
#100
b0 $
0#
#101
b1 $
1#
#102
b0 $
0#
#103
b1 $
1#
#104
b0 $
0#
#105
b1 $
1#
#106
b0 $
0#
#107
b1 $
1#
#108
b0 $
0#
#109
b1 $
1#
#110
b0 $
0#
#111
b1 $
1#
#112
b0 $
0#
#113
b1 $
1#
#114
b0 $
0#
#115
b1 $
1#
#116
b0 $
0#
#117
b1 $
1#
#118
b0 $
0#
#119
b1 $
1#
#120
b0 $
0#
#121
b1 $
1#
#122
b0 $
0#
#123
b1 $
1#
#124
b0 $
0#
#125
b1 $
1#
#126
b0 $
0#
#127
b1 $
1#
#128
b0 $
0#
#129
b1 $
1#
#130
b0 $
0#
#131
b1 $
1#
#132
b0 $
0#
#133
b1 $
1#
#134
b0 $
0#
#135
b1 $
1#
#136
b0 $
0#
#137
b1 $
1#
#138
b0 $
0#
#139
b1 $
1#
#140
b0 $
0#
#141
b1 $
1#
#142
b0 $
0#
#143
b1 $
1#
#144
b0 $
0#
#145
b1 $
1#
#146
b0 $
0#
#147
b1 $
1#
#148
b0 $
0#
#149
b1 $
1#
#150
b0 $
0#
#151
b1 $
1#
#152
b0 $
0#
#153
b1 $
1#
#154
b0 $
0#
#155
b1 $
1#
#156
b0 $
0#
#157
b1 $
1#
#158
b0 $
0#
#159
b1 $
1#
#160
b0 $
0#
#161
b1 $
1#
#162
b0 $
0#
#163
b1 $
1#
#164
b0 $
0#
#165
b1 $
1#
#166
b0 $
0#
#167
b1 $
1#
#168
b0 $
0#
#169
b1 $
1#
#170
b0 $
0#
#171
b1 $
1#
#172
b0 $
0#
#173
b1 $
1#
#174
b0 $
0#
#175
b1 $
1#
#176
b0 $
0#
#177
b1 $
1#
#178
b0 $
0#
#179
b1 $
1#
#180
b0 $
0#
#181
b1 $
1#
#182
b0 $
0#
#183
b1 $
1#
#184
b0 $
0#
#185
b1 $
1#
#186
b0 $
0#
#187
b1 $
1#
#188
b0 $
0#
#189
b1 $
1#
#190
b0 $
0#
#191
b1 $
1#
#192
b0 $
0#
#193
b1 $
1#
#194
b0 $
0#
#195
b1 $
1#
#196
b0 $
0#
#197
b1 $
1#
#198
b0 $
0#
#199
b1 $
1#
#200
b0 $
0#
#201
b1 $
1#
#202
b0 $
0#
#203
b1 $
1#
#204
b0 $
0#
#205
b1 $
1#
#206
b0 $
0#
#207
b1 $
1#
#208
b0 $
0#
#209
b1 $
1#
#210
b0 $
0#
#211
b1 $
1#
#212
b0 $
0#
#213
b1 $
1#
#214
b0 $
0#
#215
b1 $
1#
#216
b0 $
0#
#217
b1 $
1#
#218
b0 $
0#
#219
b1 $
1#
#220
b0 $
0#
#221
b1 $
1#
#222
b0 $
0#
#223
b1 $
1#
#224
b0 $
0#
#225
b1 $
1#
#226
b0 $
0#
#227
b1 $
1#
#228
b0 $
0#
#229
b1 $
1#
#230
b0 $
0#
#231
b1 $
1#
#232
b0 $
0#
#233
b1 $
1#
#234
b0 $
0#
#235
b1 $
1#
#236
b0 $
0#
#237
b1 $
1#
#238
b0 $
0#
#239
b1 $
1#
#240
b0 $
0#
#241
b1 $
1#
#242
b0 $
0#
#243
b1 $
1#
#244
b0 $
0#
#245
b1 $
1#
#246
b0 $
0#
#247
b1 $
1#
#248
b0 $
0#
#249
b1 $
1#
#250
b0 $
0#
#251
b1 $
1#
#252
b0 $
0#
#253
b1 $
1#
#254
b0 $
0#
#255
b1 $
1#
#256
b0 $
0#
#257
b1 $
1#
#258
b0 $
0#
#259
b1 $
1#
#260
b0 $
0#
#261
b1 $
1#
#262
b0 $
0#
#263
b1 $
1#
#264
b0 $
0#
#265
b1 $
1#
#266
b0 $
0#
#267
b1 $
1#
#268
b0 $
0#
#269
b1 $
1#
#270
b0 $
0#
#271
b1 $
1#
#272
b0 $
0#
#273
b1 $
1#
#274
b0 $
0#
#275
b1 $
1#
#276
b0 $
0#
#277
b1 $
1#
#278
b0 $
0#
#279
b1 $
1#
#280
b0 $
0#
#281
b1 $
1#
#282
b0 $
0#
#283
b1 $
1#
#284
b0 $
0#
#285
b1 $
1#
#286
b0 $
0#
#287
b1 $
1#
#288
b0 $
0#
#289
b1 $
1#
#290
b0 $
0#
#291
b1 $
1#
#292
b0 $
0#
#293
b1 $
1#
#294
b0 $
0#
#295
b1 $
1#
#296
b0 $
0#
#297
b1 $
1#
#298
b0 $
0#
#299
b1 $
1#
#300
b0 $
0#
#301
b1 $
1#
#302
b0 $
0#
#303
b1 $
1#
#304
b0 $
0#
#305
b1 $
1#
#306
b0 $
0#
#307
b1 $
1#
#308
b0 $
0#
#309
b1 $
1#
#310
b0 $
0#
#311
b1 $
1#
#312
b0 $
0#
#313
b1 $
1#
#314
b0 $
0#
#315
b1 $
1#
#316
b0 $
0#
#317
b1 $
1#
#318
b0 $
0#
#319
b1 $
1#
#320
b0 $
0#
#321
b1 $
1#
#322
b0 $
0#
#323
b1 $
1#
#324
b0 $
0#
#325
b1 $
1#
#326
b0 $
0#
#327
b1 $
1#
#328
b0 $
0#
#329
b1 $
1#
#330
b0 $
0#
#331
b1 $
1#
#332
b0 $
0#
#333
b1 $
1#
#334
b0 $
0#
#335
b1 $
1#
#336
b0 $
0#
#337
b1 $
1#
#338
b0 $
0#
#339
b1 $
1#
#340
b0 $
0#
#341
b1 $
1#
#342
b0 $
0#
#343
b1 $
1#
#344
b0 $
0#
#345
b1 $
1#
#346
b0 $
0#
#347
b1 $
1#
#348
b0 $
0#
#349
b1 $
1#
#350
b0 $
0#
#351
b1 $
1#
#352
b0 $
0#
#353
b1 $
1#
#354
b0 $
0#
#355
b1 $
1#
#356
b0 $
0#
#357
b1 $
1#
#358
b0 $
0#
#359
b1 $
1#
#360
b0 $
0#
#361
b1 $
1#
#362
b0 $
0#
#363
b1 $
1#
#364
b0 $
0#
#365
b1 $
1#
#366
b0 $
0#
#367
b1 $
1#
#368
b0 $
0#
#369
b1 $
1#
#370
b0 $
0#
#371
b1 $
1#
#372
b0 $
0#
#373
b1 $
1#
#374
b0 $
0#
#375
b1 $
1#
#376
b0 $
0#
#377
b1 $
1#
#378
b0 $
0#
#379
b1 $
1#
#380
b0 $
0#
#381
b1 $
1#
#382
b0 $
0#
#383
b1 $
1#
#384
b0 $
0#
#385
b1 $
1#
#386
b0 $
0#
#387
b1 $
1#
#388
b0 $
0#
#389
b1 $
1#
#390
b0 $
0#
#391
b1 $
1#
#392
b0 $
0#
#393
b1 $
1#
#394
b0 $
0#
#395
b1 $
1#
#396
b0 $
0#
#397
b1 $
1#
#398
b0 $
0#
#399
b1 $
1#
#400
b0 $
0#
#401
b1 $
1#
#402
b0 $
0#
#403
b1 $
1#
#404
b0 $
0#
#405
b1 $
1#
#406
b0 $
0#
#407
b1 $
1#
#408
b0 $
0#
#409
b1 $
1#
#410
b0 $
0#
#411
b1 $
1#
#412
b0 $
0#
#413
b1 $
1#
#414
b0 $
0#
#415
b1 $
1#
#416
b0 $
0#
#417
b1 $
1#
#418
b0 $
0#
#419
b1 $
1#
#420
b0 $
0#
#421
b1 $
1#
#422
b0 $
0#
#423
b1 $
1#
#424
b0 $
0#
#425
b1 $
1#
#426
b0 $
0#
#427
b1 $
1#
#428
b0 $
0#
#429
b1 $
1#
#430
b0 $
0#
#431
b1 $
1#
#432
b0 $
0#
#433
b1 $
1#
#434
b0 $
0#
#435
b1 $
1#
#436
b0 $
0#
#437
b1 $
1#
#438
b0 $
0#
#439
b1 $
1#
#440
b0 $
0#
#441
b1 $
1#
#442
b0 $
0#
#443
b1 $
1#
#444
b0 $
0#
#445
b1 $
1#
#446
b0 $
0#
#447
b1 $
1#
#448
b0 $
0#
#449
b1 $
1#
#450
b0 $
0#
#451
b1 $
1#
#452
b0 $
0#
#453
b1 $
1#
#454
b0 $
0#
#455
b1 $
1#
#456
b0 $
0#
#457
b1 $
1#
#458
b0 $
0#
#459
b1 $
1#
#460
b0 $
0#
#461
b1 $
1#
#462
b0 $
0#
#463
b1 $
1#
#464
b0 $
0#
#465
b1 $
1#
#466
b0 $
0#
#467
b1 $
1#
#468
b0 $
0#
#469
b1 $
1#
#470
b0 $
0#
#471
b1 $
1#
#472
b0 $
0#
#473
b1 $
1#
#474
b0 $
0#
#475
b1 $
1#
#476
b0 $
0#
#477
b1 $
1#
#478
b0 $
0#
#479
b1 $
1#
#480
b0 $
0#
#481
b1 $
1#
#482
b0 $
0#
#483
b1 $
1#
#484
b0 $
0#
#485
b1 $
1#
#486
b0 $
0#
#487
b1 $
1#
#488
b0 $
0#
#489
b1 $
1#
#490
b0 $
0#
#491
b1 $
1#
#492
b0 $
0#
#493
b1 $
1#
#494
b0 $
0#
#495
b1 $
1#
#496
b0 $
0#
#497
b1 $
1#
#498
b0 $
0#
#499
b1 $
1#
#500
b0 $
0#
#501
b1 $
1#
#502
b0 $
0#
#503
b1 $
1#
#504
b0 $
0#
#505
b1 $
1#
#506
b0 $
0#
#507
b1 $
1#
#508
b0 $
0#
#509
b1 $
1#
#510
b0 $
0#
#511
b1 $
1#
#512
b0 $
0#
#513
b1 $
1#
#514
b0 $
0#
#515
b1 $
1#
#516
b0 $
0#
#517
b1 $
1#
#518
b0 $
0#
#519
b1 $
1#
#520
b0 $
0#
#521
b1 $
1#
#522
b0 $
0#
#523
b1 $
1#
#524
b0 $
0#
#525
b1 $
1#
#526
b0 $
0#
#527
b1 $
1#
#528
b0 $
0#
#529
b1 $
1#
#530
b0 $
0#
#531
b1 $
1#
#532
b0 $
0#
#533
b1 $
1#
#534
b0 $
0#
#535
b1 $
1#
#536
b0 $
0#
#537
b1 $
1#
#538
b0 $
0#
#539
b1 $
1#
#540
b0 $
0#
#541
b1 $
1#
#542
b0 $
0#
#543
b1 $
1#
#544
b0 $
0#
#545
b1 $
1#
#546
b0 $
0#
#547
b1 $
1#
#548
b0 $
0#
#549
b1 $
1#
#550
b0 $
0#
#551
b1 $
1#
#552
b0 $
0#
#553
b1 $
1#
#554
b0 $
0#
#555
b1 $
1#
#556
b0 $
0#
#557
b1 $
1#
#558
b0 $
0#
#559
b1 $
1#
#560
b0 $
0#
#561
b1 $
1#
#562
b0 $
0#
#563
b1 $
1#
#564
b0 $
0#
#565
b1 $
1#
#566
b0 $
0#
#567
b1 $
1#
#568
b0 $
0#
#569
b1 $
1#
#570
b0 $
0#
#571
b1 $
1#
#572
b0 $
0#
#573
b1 $
1#
#574
b0 $
0#
#575
b1 $
1#
#576
b0 $
0#
#577
b1 $
1#
#578
b0 $
0#
#579
b1 $
1#
#580
b0 $
0#
#581
b1 $
1#
#582
b0 $
0#
#583
b1 $
1#
#584
b0 $
0#
#585
b1 $
1#
#586
b0 $
0#
#587
b1 $
1#
#588
b0 $
0#
#589
b1 $
1#
#590
b0 $
0#
#591
b1 $
1#
#592
b0 $
0#
#593
b1 $
1#
#594
b0 $
0#
#595
b1 $
1#
#596
b0 $
0#
#597
b1 $
1#
#598
b0 $
0#
#599
b1 $
1#
#600
b0 $
0#
#601
b1 $
1#
#602
b0 $
0#
#603
b1 $
1#
#604
b0 $
0#
#605
b1 $
1#
#606
b0 $
0#
#607
b1 $
1#
#608
b0 $
0#
#609
b1 $
1#
#610
b0 $
0#
#611
b1 $
1#
#612
b0 $
0#
#613
b1 $
1#
#614
b0 $
0#
#615
b1 $
1#
#616
b0 $
0#
#617
b1 $
1#
#618
b0 $
0#
#619
b1 $
1#
#620
b0 $
0#
#621
b1 $
1#
#622
b0 $
0#
#623
b1 $
1#
#624
b0 $
0#
#625
b1 $
1#
#626
b0 $
0#
#627
b1 $
1#
#628
b0 $
0#
#629
b1 $
1#
#630
b0 $
0#
#631
b1 $
1#
#632
b0 $
0#
#633
b1 $
1#
#634
b0 $
0#
#635
b1 $
1#
#636
b0 $
0#
#637
b1 $
1#
#638
b0 $
0#
#639
b1 $
1#
#640
b0 $
0#
#641
b1 $
1#
#642
b0 $
0#
#643
b1 $
1#
#644
b0 $
0#
#645
b1 $
1#
#646
b0 $
0#
#647
b1 $
1#
#648
b0 $
0#
#649
b1 $
1#
#650
b0 $
0#
#651
b1 $
1#
#652
b0 $
0#
#653
b1 $
1#
#654
b0 $
0#
#655
b1 $
1#
#656
b0 $
0#
#657
b1 $
1#
#658
b0 $
0#
#659
b1 $
1#
#660
b0 $
0#
#661
b1 $
1#
#662
b0 $
0#
#663
b1 $
1#
#664
b0 $
0#
#665
b1 $
1#
#666
b0 $
0#
#667
b1 $
1#
#668
b0 $
0#
#669
b1 $
1#
#670
b0 $
0#
#671
b1 $
1#
#672
b0 $
0#
#673
b1 $
1#
#674
b0 $
0#
#675
b1 $
1#
#676
b0 $
0#
#677
b1 $
1#
#678
b0 $
0#
#679
b1 $
1#
#680
b0 $
0#
#681
b1 $
1#
#682
b0 $
0#
#683
b1 $
1#
#684
b0 $
0#
#685
b1 $
1#
#686
b0 $
0#
#687
b1 $
1#
#688
b0 $
0#
#689
b1 $
1#
#690
b0 $
0#
#691
b1 $
1#
#692
b0 $
0#
#693
b1 $
1#
#694
b0 $
0#
#695
b1 $
1#
#696
b0 $
0#
#697
b1 $
1#
#698
b0 $
0#
#699
b1 $
1#
#700
b0 $
0#
#701
b1 $
1#
#702
b0 $
0#
#703
b1 $
1#
#704
b0 $
0#
#705
b1 $
1#
#706
b0 $
0#
#707
b1 $
1#
#708
b0 $
0#
#709
b1 $
1#
#710
b0 $
0#
#711
b1 $
1#
#712
b0 $
0#
#713
b1 $
1#
#714
b0 $
0#
#715
b1 $
1#
#716
b0 $
0#
#717
b1 $
1#
#718
b0 $
0#
#719
b1 $
1#
#720
b0 $
0#
#721
b1 $
1#
#722
b0 $
0#
#723
b1 $
1#
#724
b0 $
0#
#725
b1 $
1#
#726
b0 $
0#
#727
b1 $
1#
#728
b0 $
0#
#729
b1 $
1#
#730
b0 $
0#
#731
b1 $
1#
#732
b0 $
0#
#733
b1 $
1#
#734
b0 $
0#
#735
b1 $
1#
#736
b0 $
0#
#737
b1 $
1#
#738
b0 $
0#
#739
b1 $
1#
#740
b0 $
0#
#741
b1 $
1#
#742
b0 $
0#
#743
b1 $
1#
#744
b0 $
0#
#745
b1 $
1#
#746
b0 $
0#
#747
b1 $
1#
#748
b0 $
0#
#749
b1 $
1#
#750
b0 $
0#
#751
b1 $
1#
#752
b0 $
0#
#753
b1 $
1#
#754
b0 $
0#
#755
b1 $
1#
#756
b0 $
0#
#757
b1 $
1#
#758
b0 $
0#
#759
b1 $
1#
#760
b0 $
0#
#761
b1 $
1#
#762
b0 $
0#
#763
b1 $
1#
#764
b0 $
0#
#765
b1 $
1#
#766
b0 $
0#
#767
b1 $
1#
#768
b0 $
0#
#769
b1 $
1#
#770
b0 $
0#
#771
b1 $
1#
#772
b0 $
0#
#773
b1 $
1#
#774
b0 $
0#
#775
b1 $
1#
#776
b0 $
0#
#777
b1 $
1#
#778
b0 $
0#
#779
b1 $
1#
#780
b0 $
0#
#781
b1 $
1#
#782
b0 $
0#
#783
b1 $
1#
#784
b0 $
0#
#785
b1 $
1#
#786
b0 $
0#
#787
b1 $
1#
#788
b0 $
0#
#789
b1 $
1#
#790
b0 $
0#
#791
b1 $
1#
#792
b0 $
0#
#793
b1 $
1#
#794
b0 $
0#
#795
b1 $
1#
#796
b0 $
0#
#797
b1 $
1#
#798
b0 $
0#
#799
b1 $
1#
#800
b0 $
0#
#801
b1 $
1#
#802
b0 $
0#
#803
b1 $
1#
#804
b0 $
0#
#805
b1 $
1#
#806
b0 $
0#
#807
b1 $
1#
#808
b0 $
0#
#809
b1 $
1#
#810
b0 $
0#
#811
b1 $
1#
#812
b0 $
0#
#813
b1 $
1#
#814
b0 $
0#
#815
b1 $
1#
#816
b0 $
0#
#817
b1 $
1#
#818
b0 $
0#
#819
b1 $
1#
#820
b0 $
0#
#821
b1 $
1#
#822
b0 $
0#
#823
b1 $
1#
#824
b0 $
0#
#825
b1 $
1#
#826
b0 $
0#
#827
b1 $
1#
#828
b0 $
0#
#829
b1 $
1#
#830
b0 $
0#
#831
b1 $
1#
#832
b0 $
0#
#833
b1 $
1#
#834
b0 $
0#
#835
b1 $
1#
#836
b0 $
0#
#837
b1 $
1#
#838
b0 $
0#
#839
b1 $
1#
#840
b0 $
0#
#841
b1 $
1#
#842
b0 $
0#
#843
b1 $
1#
#844
b0 $
0#
#845
b1 $
1#
#846
b0 $
0#
#847
b1 $
1#
#848
b0 $
0#
#849
b1 $
1#
#850
b0 $
0#
#851
b1 $
1#
#852
b0 $
0#
#853
b1 $
1#
#854
b0 $
0#
#855
b1 $
1#
#856
b0 $
0#
#857
b1 $
1#
#858
b0 $
0#
#859
b1 $
1#
#860
b0 $
0#
#861
b1 $
1#
#862
b0 $
0#
#863
b1 $
1#
#864
b0 $
0#
#865
b1 $
1#
#866
b0 $
0#
#867
b1 $
1#
#868
b0 $
0#
#869
b1 $
1#
#870
b0 $
0#
#871
b1 $
1#
#872
b0 $
0#
#873
b1 $
1#
#874
b0 $
0#
#875
b1 $
1#
#876
b0 $
0#
#877
b1 $
1#
#878
b0 $
0#
#879
b1 $
1#
#880
b0 $
0#
#881
b1 $
1#
#882
b0 $
0#
#883
b1 $
1#
#884
b0 $
0#
#885
b1 $
1#
#886
b0 $
0#
#887
b1 $
1#
#888
b0 $
0#
#889
b1 $
1#
#890
b0 $
0#
#891
b1 $
1#
#892
b0 $
0#
#893
b1 $
1#
#894
b0 $
0#
#895
b1 $
1#
#896
b0 $
0#
#897
b1 $
1#
#898
b0 $
0#
#899
b1 $
1#
#900
b0 $
0#
#901
b1 $
1#
#902
b0 $
0#
#903
b1 $
1#
#904
b0 $
0#
#905
b1 $
1#
#906
b0 $
0#
#907
b1 $
1#
#908
b0 $
0#
#909
b1 $
1#
#910
b0 $
0#
#911
b1 $
1#
#912
b0 $
0#
#913
b1 $
1#
#914
b0 $
0#
#915
b1 $
1#
#916
b0 $
0#
#917
b1 $
1#
#918
b0 $
0#
#919
b1 $
1#
#920
b0 $
0#
#921
b1 $
1#
#922
b0 $
0#
#923
b1 $
1#
#924
b0 $
0#
#925
b1 $
1#
#926
b0 $
0#
#927
b1 $
1#
#928
b0 $
0#
#929
b1 $
1#
#930
b0 $
0#
#931
b1 $
1#
#932
b0 $
0#
#933
b1 $
1#
#934
b0 $
0#
#935
b1 $
1#
#936
b0 $
0#
#937
b1 $
1#
#938
b0 $
0#
#939
b1 $
1#
#940
b0 $
0#
#941
b1 $
1#
#942
b0 $
0#
#943
b1 $
1#
#944
b0 $
0#
#945
b1 $
1#
#946
b0 $
0#
#947
b1 $
1#
#948
b0 $
0#
#949
b1 $
1#
#950
b0 $
0#
#951
b1 $
1#
#952
b0 $
0#
#953
b1 $
1#
#954
b0 $
0#
#955
b1 $
1#
#956
b0 $
0#
#957
b1 $
1#
#958
b0 $
0#
#959
b1 $
1#
#960
b0 $
0#
#961
b1 $
1#
#962
b0 $
0#
#963
b1 $
1#
#964
b0 $
0#
#965
b1 $
1#
#966
b0 $
0#
#967
b1 $
1#
#968
b0 $
0#
#969
b1 $
1#
#970
b0 $
0#
#971
b1 $
1#
#972
b0 $
0#
#973
b1 $
1#
#974
b0 $
0#
#975
b1 $
1#
#976
b0 $
0#
#977
b1 $
1#
#978
b0 $
0#
#979
b1 $
1#
#980
b0 $
0#
#981
b1 $
1#
#982
b0 $
0#
#983
b1 $
1#
#984
b0 $
0#
#985
b1 $
1#
#986
b0 $
0#
#987
b1 $
1#
#988
b0 $
0#
#989
b1 $
1#
#990
b0 $
0#
#991
b1 $
1#
#992
b0 $
0#
#993
b1 $
1#
#994
b0 $
0#
#995
b1 $
1#
#996
b0 $
0#
#997
b1 $
1#
#998
b0 $
0#
#999
b1 $
1#
#1000
b0 $
0#
#1001
b1 $
1#
